great_dataset/__init__.py
great_dataset/function_set.py
greatdataset-0.0.1.dist-info/LICENSE
greatdataset-0.0.1.dist-info/METADATA
greatdataset-0.0.1.dist-info/WHEEL
greatdataset-0.0.1.dist-info/top_level.txt
greatdataset-0.0.1.dist-info/RECORD
